conda_env_export/__init__.py
conda_env_export/cli.py
conda_env_export/conda_env_export.py
conda_env_export-0.6.1.dist-info/AUTHORS.rst
conda_env_export-0.6.1.dist-info/LICENSE
conda_env_export-0.6.1.dist-info/METADATA
conda_env_export-0.6.1.dist-info/WHEEL
conda_env_export-0.6.1.dist-info/entry_points.txt
conda_env_export-0.6.1.dist-info/top_level.txt
conda_env_export-0.6.1.dist-info/RECORD
