Metadata-Version: 2.1
Name: conda-env-export
Version: 0.6.1
Summary: Export conda env dependencies and pip requirements to ONE yml file.
Home-page: https://github.com/luffy-yu/conda_env_export
Author: Luffy Yu
Author-email: yuliuchuan@gmail.com
License: MIT license
Keywords: conda_env_export
Platform: UNKNOWN
Classifier: Development Status :: 2 - Pre-Alpha
Classifier: Intended Audience :: Developers
Classifier: License :: OSI Approved :: MIT License
Classifier: Natural Language :: English
Classifier: Programming Language :: Python :: 3
Classifier: Programming Language :: Python :: 3.5
Classifier: Programming Language :: Python :: 3.6
Classifier: Programming Language :: Python :: 3.7
Classifier: Programming Language :: Python :: 3.8
Classifier: Programming Language :: Python :: 3.9
Classifier: Programming Language :: Python :: 3.10
Classifier: Programming Language :: Python :: 3.11
Requires-Python: >=3.5
License-File: LICENSE
License-File: AUTHORS.rst
Requires-Dist: setuptools
Requires-Dist: Click (>=7.0)
Requires-Dist: cytoolz (>=0.11.0)
Requires-Dist: PyYAML (>=5.1)
Requires-Dist: ruamel.yaml (<0.18,>=0.11.14)
